flask_opentracing/__init__.py
flask_opentracing/tracing.py
tests/__init__.py
tests/test_flask_api.py
tests/test_flask_tracing.py
tests/test_flask_tracing_span_callbacks.py
Flask_OpenTracing-2.0.0.dist-info/LICENSE
Flask_OpenTracing-2.0.0.dist-info/METADATA
Flask_OpenTracing-2.0.0.dist-info/WHEEL
Flask_OpenTracing-2.0.0.dist-info/top_level.txt
Flask_OpenTracing-2.0.0.dist-info/RECORD
