Metadata-Version: 2.1
Name: Flask-OpenTracing
Version: 2.0.0
Summary: OpenTracing support for Flask applications
Home-page: http://github.com/opentracing-contrib/python-flask
Download-URL: https://github.com/opentracing-contrib/python-flask/tarball/2.0.0
Author: Kathy Camenzind
Author-email: kcamenzind@lightstep.com
License: BSD
Platform: any
Classifier: Environment :: Web Environment
Classifier: Intended Audience :: Developers
Classifier: License :: OSI Approved :: BSD License
Classifier: Operating System :: OS Independent
Classifier: Programming Language :: Python
Classifier: Programming Language :: Python :: 3
Classifier: Programming Language :: Python :: 3.8
Classifier: Programming Language :: Python :: 3.9
Classifier: Programming Language :: Python :: 3.10
Classifier: Programming Language :: Python :: 3.11
Classifier: Programming Language :: Python :: 3.12
Classifier: Programming Language :: Python :: Implementation :: CPython
Classifier: Programming Language :: Python :: Implementation :: PyPy
Classifier: Development Status :: 7 - Inactive
Classifier: Topic :: Internet :: WWW/HTTP :: Dynamic Content
Classifier: Topic :: Software Development :: Libraries :: Python Modules
License-File: LICENSE
Requires-Dist: Flask
Requires-Dist: opentracing<3,>=2.0
Provides-Extra: tests
Requires-Dist: flake8; extra == "tests"
Requires-Dist: flake8-quotes; extra == "tests"
Requires-Dist: mock; extra == "tests"
Requires-Dist: pytest; extra == "tests"
Requires-Dist: pytest-cov; extra == "tests"
Requires-Dist: tox; extra == "tests"
